horde_engine-2.22.2.dist-info/licenses/CHANGELOG.md
horde_engine-2.22.2.dist-info/licenses/LICENSE
hordelib/__init__.py
hordelib/__pyinstaller.py
hordelib/_version.py
hordelib/benchmark.py
hordelib/comfy_horde.py
hordelib/config_path.py
hordelib/consts.py
hordelib/exceptions.py
hordelib/horde.py
hordelib/initialisation.py
hordelib/install_comfy.py
hordelib/preload.py
hordelib/py.typed
hordelib/safety.py
hordelib/safety_checker.py
hordelib/settings.py
hordelib/shared_model_manager.py
hordelib/train.py
hordelib/_comfyui/.gitattributes
hordelib/_comfyui/.gitignore
hordelib/_comfyui/CODEOWNERS
hordelib/_comfyui/CONTRIBUTING.md
hordelib/_comfyui/LICENSE
hordelib/_comfyui/QUANTIZATION.md
hordelib/_comfyui/README.md
hordelib/_comfyui/alembic.ini
hordelib/_comfyui/comfyui_version.py
hordelib/_comfyui/cuda_malloc.py
hordelib/_comfyui/execution.py
hordelib/_comfyui/extra_model_paths.yaml
hordelib/_comfyui/extra_model_paths.yaml.example
hordelib/_comfyui/folder_paths.py
hordelib/_comfyui/hook_breaker_ac10a0.py
hordelib/_comfyui/latent_preview.py
hordelib/_comfyui/main.py
hordelib/_comfyui/new_updater.py
hordelib/_comfyui/node_helpers.py
hordelib/_comfyui/nodes.py
hordelib/_comfyui/protocol.py
hordelib/_comfyui/pyproject.toml
hordelib/_comfyui/pytest.ini
hordelib/_comfyui/requirements.txt
hordelib/_comfyui/server.py
hordelib/_comfyui/alembic_db/README.md
hordelib/_comfyui/alembic_db/env.py
hordelib/_comfyui/alembic_db/script.py.mako
hordelib/_comfyui/api_server/__init__.py
hordelib/_comfyui/api_server/routes/__init__.py
hordelib/_comfyui/api_server/routes/internal/README.md
hordelib/_comfyui/api_server/routes/internal/__init__.py
hordelib/_comfyui/api_server/routes/internal/internal_routes.py
hordelib/_comfyui/api_server/services/__init__.py
hordelib/_comfyui/api_server/services/terminal_service.py
hordelib/_comfyui/api_server/utils/file_operations.py
hordelib/_comfyui/app/__init__.py
hordelib/_comfyui/app/app_settings.py
hordelib/_comfyui/app/custom_node_manager.py
hordelib/_comfyui/app/frontend_management.py
hordelib/_comfyui/app/logger.py
horde_engine-2.22.2.dist-info/METADATA
horde_engine-2.22.2.dist-info/WHEEL
horde_engine-2.22.2.dist-info/entry_points.txt
horde_engine-2.22.2.dist-info/top_level.txt
horde_engine-2.22.2.dist-info/RECORD
