Metadata-Version: 2.4
Name: horde-engine
Version: 2.22.2
Summary: A wrapper around ComfyUI to allow use by AI Horde.
Author-email: tazlin <tazlin.on.github@gmail.com>, db0 <mail@dbzer0.com>, Jug <jugdev@proton.me>
License:                     GNU AFFERO GENERAL PUBLIC LICENSE
Project-URL: Homepage, https://github.com/Haidra-Org/hordelib
Project-URL: Bug Tracker, https://github.com/Haidra-Org/hordelib/issues
Project-URL: Changelog, https://github.com/Haidra-Org/hordelib/blob/releases/CHANGELOG.md
Classifier: Programming Language :: Python :: 3
Classifier: License :: OSI Approved :: GNU Affero General Public License v3
Classifier: Operating System :: OS Independent
Classifier: Development Status :: 5 - Production/Stable
Requires-Python: >=3.10
License-File: LICENSE
License-File: CHANGELOG.md
Requires-Dist: horde_sdk>=0.15.0
Requires-Dist: horde_model_reference>=0.9.1
Requires-Dist: numpy==1.26.4
Requires-Dist: torch>=2.4.1
Requires-Dist: torchvision
Requires-Dist: torchdiffeq
Requires-Dist: torchsde
Requires-Dist: einops
Requires-Dist: open-clip-torch
Requires-Dist: transformers>=4.37.2
Requires-Dist: tokenizers>=0.13.3
Requires-Dist: sentencepiece
Requires-Dist: safetensors>=0.4.2
Requires-Dist: pytorch_lightning
Requires-Dist: pynvml
Requires-Dist: aiohttp>=3.11.8
Requires-Dist: accelerate
Requires-Dist: pyyaml
Requires-Dist: pillow
Requires-Dist: loguru
Requires-Dist: GitPython
Requires-Dist: clip-anytorch
Requires-Dist: diffusers>=0.25.0
Requires-Dist: omegaconf
Requires-Dist: psutil
Requires-Dist: typing-extensions
Requires-Dist: distro
Requires-Dist: python-dotenv
Requires-Dist: strenum
Requires-Dist: rembg[cpu]
Requires-Dist: opencv-python
Requires-Dist: opencv-contrib-python
Requires-Dist: opencv-python
Requires-Dist: timm==0.9.16
Requires-Dist: torchvision
Requires-Dist: scipy
Requires-Dist: addict
Requires-Dist: fairscale
Requires-Dist: scikit-image
Requires-Dist: mediapipe==0.10.21
Requires-Dist: unidecode
Requires-Dist: fuzzywuzzy
Requires-Dist: strenum
Requires-Dist: kornia
Requires-Dist: qrcode==7.4.2
Requires-Dist: spandrel
Requires-Dist: spandrel_extra_arches
Requires-Dist: soundfile
Requires-Dist: lpips
Requires-Dist: av>=14.2.0
Requires-Dist: pydantic~=2.0
Requires-Dist: pydantic-settings~=2.0
Requires-Dist: SQLAlchemy
Requires-Dist: alembic
Requires-Dist: tqdm
Requires-Dist: yarl>=1.18.0
Requires-Dist: comfyui-frontend-package==1.25.11
Requires-Dist: comfyui-workflow-templates==0.1.75
Requires-Dist: comfyui-embedded-docs==0.2.6
Dynamic: license-file
